simplefractions/__init__.py
simplefractions/_simplest_in_interval.py
simplefractions/py.typed
simplefractions/test/__init__.py
simplefractions/test/test_simplefractions.py
simplefractions-1.3.0.dist-info/licenses/LICENSE
simplefractions-1.3.0.dist-info/METADATA
simplefractions-1.3.0.dist-info/WHEEL
simplefractions-1.3.0.dist-info/top_level.txt
simplefractions-1.3.0.dist-info/RECORD
