Metadata-Version: 2.4
Name: simplefractions
Version: 1.3.0
Summary: Find the simplest fraction for a given float or interval
Author-email: Mark Dickinson <dickinsm@gmail.com>
Project-URL: source, https://github.com/mdickinson/simplefractions
Keywords: fractions,continued fractions,approximation
Classifier: License :: OSI Approved :: Apache Software License
Classifier: Operating System :: OS Independent
Classifier: Programming Language :: Python :: 3
Classifier: Topic :: Scientific/Engineering :: Mathematics
Requires-Python: >=3.8
License-File: LICENSE
Dynamic: license-file
